apygee/__init__.py
apygee/constants.py
apygee/kepler.py
apygee/orbit.py
apygee/plot.py
apygee/utils.py
apygee-1.0.5.dist-info/LICENSE.md
apygee-1.0.5.dist-info/METADATA
apygee-1.0.5.dist-info/WHEEL
apygee-1.0.5.dist-info/RECORD
