Metadata-Version: 2.1
Name: apygee
Version: 1.0.5
Summary: A package for creating, manipulating and visualizing Kepler orbits
Author: Jelmar Gerritsen
Author-email: jelmargerritsen@gmail.com
Requires-Python: >=3.12,<4.0
Classifier: Programming Language :: Python :: 3
Classifier: Programming Language :: Python :: 3.12
Requires-Dist: ipywidgets (>=8.1.2,<9.0.0)
Requires-Dist: matplotlib (>=3.8.3,<4.0.0)
Requires-Dist: numpy (>=1.26.4,<2.0.0)
Requires-Dist: pandas (>=2.2.2,<3.0.0)
Requires-Dist: plotly (>=5.20.0,<6.0.0)
